scaled_preconditioners/__init__.py
scaled_preconditioners/approximation.py
scaled_preconditioners/preconditioner.py
scaled_preconditioners/utils.py
scaled_preconditioners-0.1.1.dist-info/LICENSE
scaled_preconditioners-0.1.1.dist-info/WHEEL
scaled_preconditioners-0.1.1.dist-info/METADATA
scaled_preconditioners-0.1.1.dist-info/RECORD
