Metadata-Version: 2.1
Name: scaled-preconditioners
Version: 0.1.1
Summary: 
Author: Andreas Bock
Author-email: aasbo@dtu.dk
Requires-Python: >=3.8.1,<3.12
Classifier: Programming Language :: Python :: 3
Classifier: Programming Language :: Python :: 3.10
Classifier: Programming Language :: Python :: 3.9
Requires-Dist: black (>=23.3.0,<24.0.0)
Requires-Dist: flake8 (>=6.0.0,<7.0.0)
Requires-Dist: isort (>=5.12.0,<6.0.0)
Requires-Dist: mypy (>=1.2.0,<2.0.0)
Requires-Dist: nox-poetry (>=1.0.2,<2.0.0)
Requires-Dist: pytest (>=7.3.0,<8.0.0)
Requires-Dist: scikit-learn (>=1.2.2,<2.0.0)
Requires-Dist: scipy (>=1.10.1,<2.0.0)
